jac_studio/__init__.py
jac_studio/cli.py
jac_studio/client/assets/index-BtFItD2q.js
jac_studio/client/assets/index-CIEsu-TC.css
jac_studio/client/index.html
jac_studio/client/jac_logo.png
jac_studio/client/tauri.svg
jac_studio/client/vite.svg
jac_studio-0.0.2.dist-info/METADATA
jac_studio-0.0.2.dist-info/WHEEL
jac_studio-0.0.2.dist-info/entry_points.txt
jac_studio-0.0.2.dist-info/RECORD
