Metadata-Version: 2.1
Name: jac-studio
Version: 0.0.2
Summary: This Jac plugin provides a visualization of a Jac-cloud MongoDB instance.
Home-page: https://trueselph.com
License: MIT
Keywords: jac,jaclang,jaseci,visualization,graph
Author: TrueSelph Inc.
Author-email: admin@trueselph.com
Requires-Python: >=3.12.0,<4.0.0
Classifier: License :: OSI Approved :: MIT License
Classifier: Programming Language :: Python :: 3
Classifier: Programming Language :: Python :: 3.12
Classifier: Programming Language :: Python :: 3.13
Requires-Dist: jac-cloud (>=0.1.5,<0.2.0)
Requires-Dist: jaclang (>=0.7.24,<0.8.0)
